{
    "uniqueId":{
        "type":"string"
    },
    "globalwidth":{
        "type":"number"
    },

    "image":{
        "type":"string",
        "default":""
    },
    "opacity":{
        "type":"number",
        "default":1
    },
    "overlaytransitiontime":{
        "type":"number",
        "default":0.5
    },
    "imagetransitiontime":{
        "type":"number",
        "default":0.5
    },
    "overlay":{
        "type":"boolean",
        "default":true
    },

    "imagehvreffect":{
        "type":"string",
        "default":"none"
    },
    "imagehvrfilter":{
        "type":"string",
        "default":"none"
    },
    "imageoverlayouteffect":{
        "type":"string",
        "default":"none"
    },
    "headingtext":{
        "type":"string",
        "default":"Heading"
    },
    "imageCaption":{
        "type":"string",
        "default":"This is image caption"
    },
    "buttontext":{
        "type":"string",
        "default":"Button"
    },
    "buttonlink":{
        "type":"string",
        "default":""
    },
    "buttonnewtab" : {
        "type": "boolean",
        "default":false
    },
    "overlaycolor":{
        "type":"string",
        "default":"#444"
    },
    "heading": {
        "type": "object",
        "default": {
            "font": "default",
            "size": "16px",
            "appearance": "normal",
            "letterSpacing": "0px",
            "letterCase": "none"
        }
    },
    "headingcolor":{
        "type":"string",
        "default":"black"
    },
    "headingtag":{
        "type":"string",
        "default":"h2"
    },
    "caption": {
        "type": "object",
        "default": {
            "font": "default",
            "size": "16px",
            "appearance": "normal",
            "letterSpacing": "0px",
            "letterCase": "none"
        }
    },
    "captioncolor":{
        "type":"string",
        "default":"black"
    },
    "captiontag":{
        "type":"string",
        "default":"h2"
    },
    "buttonbackground":{
        "type":"string",
        "default":"black"
    },
    "buttoncolor":{
        "type":"string",
        "default":"white"
    },
    "buttonborderRadius":{
        "type":"object",
        "default":{
        "top": "3px",
        "bottom": "3px",
        "left": "3px",
        "right": "3px"
    }
    },
    "buttonborder":{
        "type":"object",
        "default":{
        "topcolor": "black",
        "topwidth": "1px",
        "topstyle": "solid",

        "bottomcolor": "black",
        "bottomwidth": "1px",
        "bottomstyle": "solid",

        "leftcolor": "black",
        "leftwidth": "1px",
        "leftstyle": "solid",

        "rightcolor": "black",
        "rightwidth": "1px",
        "rightstyle": "solid"
    }
    },
    "buttonpaddingtop":{
        "type":"string",
        "default":"5px"
    },
    "buttonpaddingbottom":{
        "type":"string",
        "default":"5px"
    },
    "buttonpaddingleft":{
        "type":"string",
        "default":"5px"
    },
    "buttonpaddingright":{
        "type":"string",
        "default":"5px"
    },
   "focalPoint": {
        "type": "object",
        "default": {
            "x": 0.5,
            "y": 0.5
        }
    },
    "imagecover":{
        "type":"string",
        "default": "cover"
    },
    "imageaspectratio":{
        "type":"string",
        "default":"orginal"
    },
    "duotone": {
        "type":"string",
        "default":""
    },
    "showPreview":{
        "type":"boolean",
        "default":false
    }


}
